adjectives.py
almost_unique_id.py
names.py
almost_unique_id-0.0.3.dist-info/LICENSE.md
almost_unique_id-0.0.3.dist-info/METADATA
almost_unique_id-0.0.3.dist-info/WHEEL
almost_unique_id-0.0.3.dist-info/top_level.txt
almost_unique_id-0.0.3.dist-info/RECORD
