Metadata-Version: 2.1
Name: almost_unique_id
Version: 0.0.3
Summary: Almost Unique IDs
Author: Avi Schwarzschild
License: MIT
Keywords: run ids
Requires-Python: >=3.7
License-File: LICENSE.md
